{
    "Header": {
        "errorCode": "0",
        "errorMsg" : "(當errorCode不為0時，請alert出errorMsg)"
    },
    "Content": {
        "flow" : {
            "flowId" : "personalInfo",
            "viewURL" : "flow/personalInfo_3.jsp",
            "currentMainStep" : "personalInfo_3",
            "currentSubStep" : "",
            "mainStep" : [
                
                {
                    "id" : "personalInfo_1",
                    "name" : "輸入資料"
                },
                {
                    "id" : "personalInfo_2",
                    "name" : "確認資料"
                },
                {
                    "id" : "personalInfo_3",
                    "name" : "變更結果"
                }
            ],
            "subStep" : [
            ]
        },
		"registerResult": "success",
        "registerDate": "2016/03/12",
        "registerTime": "14:28:56",
		"errorCode": "123",
        "errorMsg": "errorMsg",
        "isRecord":"Y",
        "id" : "A123****89",
        "name" : "鄧小文",
        "birthday" : "991122",
        "marryStatus" : "N",
        "domicilePhone" : {
            "regionCode" : "03",
            "phone" : "******11"
        },
        "telePhone" : {
            "regionCode" : "02",
            "phone" : "******11"
        },
        "mobile" : "09*****551",
        "email" : "****.titanteng@gmail.com",
        "domicileAddress" : {
            "cityId" : "03",
            "zipCode" : "222",
            "liner":"1",
            "neighborhood" : "4",
            "address" : "xxxx路44號",
            "linerName" : "XX"
        },
        "teleAddress" : {
            "cityId" : "04",
            "zipCode" : "267",
            "liner":"2",
            "neighborhood" : "5",
            "address" : "xxxx路35號",
            "linerName" : "XX"
        }
    }
}