{
    "prepare" : [
        {
            "id" : "1",
            "title" : "什麼學校可以申請就學貸款?",
            "answer" : "就學貸款的承辦銀行，依主管機關規定係按學校所在地之行政區劃分，凡高級中等以上學校所在地屬台北市地區者，由本行承辦就學貸款業務。?"
        },
        {
            "id" : "2",
            "title" : "就學貸款的開放時間是什麼時候?",
            "answer" : "就學貸款開放申請時間分為上下學期，上學期自8/1~9/30；下學期申請時間自1/15~2/28。"
        },
        {
            "id" : "3",
            "title" : "就學貸款的申請資格?",
            "answer" : "就學貸款開放申請時間分為上下學期，上學期自8/1~9/30；下學期申請時間自1/15~2/28。"
        },
        {
            "id" : "4",
            "title" : "就學貸款的利率是多少?",
            "answer" : "就學貸款開放申請時間分為上下學期，上學期自8/1~9/30；下學期申請時間自1/15~2/28。"
        }
    ],
    "apply" : [
         {
            "id" : "1",
            "title" : "什麼是教育補助費?享有公費?",
            "answer" : "您可透過本行或其他銀行有跨行服務標誌的提款機轉帳繳納台北富邦銀行就學貸款，請輸入銀行代碼012，轉帳帳號為您於本行的就學貸款帳號共16碼以及轉帳金額；如有任何問題請撥打客服專線02-8751-6665按5。"
        },
        {
            "id" : "2",
            "title" : "申請後資料不齊全，怎麼辦?",
            "answer" : "您可透過本行或其他銀行有跨行服務標誌的提款機轉帳繳納台北富邦銀行就學貸款，請輸入銀行代碼012，轉帳帳號為您於本行的就學貸款帳號共16碼以及轉帳金額；如有任何問題請撥打客服專線02-8751-6665按5。"
        },
        {
            "id" : "3",
            "title" : "填寫完申請書後就算申請貸款成功了嗎?",
            "answer" : "您可透過本行或其他銀行有跨行服務標誌的提款機轉帳繳納台北富邦銀行就學貸款，請輸入銀行代碼012，轉帳帳號為您於本行的就學貸款帳號共16碼以及轉帳金額；如有任何問題請撥打客服專線02-8751-6665按5。"
        }
    ],
    "question" : [
         {
            "id" : "1",
            "title" : "什麼時候要開始還就學貸款?",
            "answer" : "就讀非在職專班學生，應自最後教育階段學程學業完成後滿一年之次日開始本息攤還。在職專班學生，應自最後教育學程學業完成後之次日開始本息攤還。"
        },
        {
            "id" : "2",
            "title" : "開始還錢會通知我嗎?",
            "answer" : "就讀非在職專班學生，應自最後教育階段學程學業完成後滿一年之次日開始本息攤還。在職專班學生，應自最後教育學程學業完成後之次日開始本息攤還。"
        },
        {
            "id" : "3",
            "title" : "貸款後怎麼還錢?",
            "answer" : "就讀非在職專班學生，應自最後教育階段學程學業完成後滿一年之次日開始本息攤還。在職專班學生，應自最後教育學程學業完成後之次日開始本息攤還。"
        },
        {
            "id" : "4",
            "title" : "如果我忘記繳款會怎樣?",
            "answer" : "就讀非在職專班學生，應自最後教育階段學程學業完成後滿一年之次日開始本息攤還。在職專班學生，應自最後教育學程學業完成後之次日開始本息攤還。"
        }
    ],
    "repayment" : [
         {
            "id" : "1",
            "title" : "就學貸款的還款方式有哪些?",
            "answer" : "就學貸款開放申請時間分為上下學期，上學期自8/1~9/30；下學期申請時間自1/15~2/28。"
        },
        {
            "id" : "2",
            "title" : "使用ATM繳就學貸款要怎麼輸入?",
            "answer" : "就學貸款開放申請時間分為上下學期，上學期自8/1~9/30；下學期申請時間自1/15~2/28。"
        }
    ]
}